ace_internal.cpython-37m-darwin.so
ace_cream/__init__.py
ace_cream/ace_cream.py
ace_internal.cpython-37m-darwin.so.dSYM/Contents/Info.plist
ace_internal.cpython-37m-darwin.so.dSYM/Contents/Resources/DWARF/ace_internal.cpython-37m-darwin.so
ace_cream-0.4.post11.dist-info/LICENSE
ace_cream-0.4.post11.dist-info/METADATA
ace_cream-0.4.post11.dist-info/WHEEL
ace_cream-0.4.post11.dist-info/top_level.txt
ace_cream-0.4.post11.dist-info/RECORD
