Metadata-Version: 2.1
Name: ace-cream
Version: 0.4.post11
Summary: Alternating Conditional Expectation Algorithm
Home-page: https://github.com/zhaofeng-shu33/ace_cream
Author: zhaofeng-shu33
Author-email: 616545598@qq.com
Maintainer: zhaofeng-shu33
Maintainer-email: 616545598@qq.com
License: Apache License Version 2.0
Platform: UNKNOWN
Classifier: Development Status :: 4 - Beta
Classifier: Programming Language :: Fortran
Classifier: Programming Language :: Python :: 3.6
Classifier: Programming Language :: Python :: 3.7
Classifier: Programming Language :: Python :: 2.7
Classifier: Operating System :: OS Independent
Requires-Dist: numpy
